ret2dl/__init__.py
ret2dl/__version__.py
ret2dl/core.py
ret2dl-0.1.1.dist-info/DESCRIPTION.rst
ret2dl-0.1.1.dist-info/METADATA
ret2dl-0.1.1.dist-info/RECORD
ret2dl-0.1.1.dist-info/WHEEL
ret2dl-0.1.1.dist-info/metadata.json
ret2dl-0.1.1.dist-info/top_level.txt
