Metadata-Version: 2.0
Name: ret2dl
Version: 0.1.1
Summary: ('Return to dl resolve exploit helper module',)
Home-page: https://github.com/bananaappletw/ret2dl
Author: Wei Bo Chen
Author-email: bananaappletw@gmail.com
License: MIT
Platform: UNKNOWN
Classifier: License :: OSI Approved :: MIT License
Classifier: Programming Language :: Python
Classifier: Programming Language :: Python :: 2.6
Classifier: Programming Language :: Python :: 3
Classifier: Programming Language :: Python :: Implementation :: CPython
Classifier: Programming Language :: Python :: Implementation :: PyPy
Requires-Python: >=2.6, <4
